LICENSE.txt
MANIFEST.in
README.rst
setup.cfg
setup.py
wio/__init__.py
wio/config.py
wio/config_default.py
wio/serial_list.py
wio/termui.py
wio/udp.py
wio/wio.py
wio/commands/__init__.py
wio/commands/cmd_call.py
wio/commands/cmd_config.py
wio/commands/cmd_delete.py
wio/commands/cmd_list.py
wio/commands/cmd_login.py
wio/commands/cmd_setup.py
wio/commands/cmd_state.py
wio/commands/cmd_udp.py
wio_cli.egg-info/PKG-INFO
wio_cli.egg-info/SOURCES.txt
wio_cli.egg-info/dependency_links.txt
wio_cli.egg-info/entry_points.txt
wio_cli.egg-info/requires.txt
wio_cli.egg-info/top_level.txt