Metadata-Version: 1.0
Name: wio-cli
Version: 0.3.2
Summary: Command line for Wio Link
Home-page: https://github.com/Seeed-Studio/wio-cli
Author: Ten Wong
Author-email: wangtengoo7@gmail.com
License: MIT
Platform: UNKNOWN
